pg_mcp_server_beta/__init__.py
pg_mcp_server_beta-1.0.dist-info/METADATA
pg_mcp_server_beta-1.0.dist-info/WHEEL
pg_mcp_server_beta-1.0.dist-info/top_level.txt
pg_mcp_server_beta-1.0.dist-info/RECORD
