Metadata-Version: 2.4
Name: pg_mcp_server_beta
Version: 1.0
Summary: 이 버전은 더 이상 사용되지 않는 테스트용 패키지입니다.
Author-email: Your Name <your@email.com>
Requires-Python: >=3.7
